{
  "KBS1": [
    {
      "start": "00:00",
      "end": "00:50",
      "title": "네트워크 공동기획 문화스케치"
    },
    {
      "start": "00:50",
      "end": "01:40",
      "title": "생활의 발견"
    },
    {
      "start": "01:40",
      "end": "02:35",
      "title": "걸어서 세계속으로 트래블홀릭"
    },
    {
      "start": "02:35",
      "end": "03:30",
      "title": "동네 한 바퀴"
    },
    {
      "start": "03:30",
      "end": "03:45",
      "title": "팔도밥상 스페셜"
    },
    {
      "start": "03:45",
      "end": "05:00",
      "title": "아침마당"
    },
    {
      "start": "05:00",
      "end": "05:10",
      "title": "생활의 발견 스페셜"
    },
    {
      "start": "05:10",
      "end": "06:00",
      "title": "내고향 스페셜"
    },
    {
      "start": "06:00",
      "end": "07:50",
      "title": "KBS 뉴스광장"
    },
    {
      "start": "07:50",
      "end": "08:25",
      "title": "인간극장"
    },
    {
      "start": "08:25",
      "end": "09:30",
      "title": "아침마당"
    },
    {
      "start": "09:30",
      "end": "10:00",
      "title": "KBS 뉴스 930"
    },
    {
      "start": "10:00",
      "end": "10:30",
      "title": "트레킹노트 세상을 걷다 스페셜"
    },
    {
      "start": "10:30",
      "end": "10:40",
      "title": "세계는 지금 스페셜"
    },
    {
      "start": "10:40",
      "end": "11:25",
      "title": "중계방송 투표용지 부족 진상규명 선관위 국정조사"
    },
    {
      "start": "11:25",
      "end": "11:30",
      "title": "불편해도 괜찮아 8"
    },
    {
      "start": "11:30",
      "end": "12:00",
      "title": "영상앨범 산"
    },
    {
      "start": "12:00",
      "end": "13:00",
      "title": "KBS 뉴스 12"
    },
    {
      "start": "13:00",
      "end": "13:50",
      "title": "KBS 네트워크 특선 지명수배 [춘천총국]"
    },
    {
      "start": "13:50",
      "end": "14:00",
      "title": "생활의 발견 스페셜"
    },
    {
      "start": "14:00",
      "end": "14:10",
      "title": "KBS 뉴스"
    },
    {
      "start": "14:10",
      "end": "14:50",
      "title": "열린채널"
    },
    {
      "start": "14:50",
      "end": "16:00",
      "title": "중계방송 투표용지 부족 진상규명 선관위 국정조사"
    },
    {
      "start": "16:00",
      "end": "17:00",
      "title": "사사건건"
    },
    {
      "start": "17:00",
      "end": "17:30",
      "title": "KBS 뉴스 5"
    },
    {
      "start": "17:30",
      "end": "18:00",
      "title": "동물의 왕국"
    },
    {
      "start": "18:00",
      "end": "19:00",
      "title": "6시 내고향"
    },
    {
      "start": "19:00",
      "end": "19:40",
      "title": "KBS 뉴스 7"
    },
    {
      "start": "19:40",
      "end": "20:30",
      "title": "황신혜의 같이 삽시다"
    },
    {
      "start": "20:30",
      "end": "21:00",
      "title": "일일드라마 기쁜 우리 좋은 날(81회)"
    },
    {
      "start": "21:00",
      "end": "22:00",
      "title": "KBS 뉴스 9"
    },
    {
      "start": "22:00",
      "end": "22:50",
      "title": "1000회 특집 생로병사의 비밀 2부"
    },
    {
      "start": "22:50",
      "end": "23:30",
      "title": "KBS 뉴스라인W"
    },
    {
      "start": "23:30",
      "end": "24:00",
      "title": "이슈 픽 쌤과 함께 스페셜"
    }
  ],
  "KBS2": [
    {
      "start": "00:20",
      "end": "00:50",
      "title": "트레킹노트 세상을 걷다 스페셜"
    },
    {
      "start": "00:50",
      "end": "01:00",
      "title": "KBS 재난방송센터"
    },
    {
      "start": "01:00",
      "end": "05:00",
      "title": "방송 시간이 아닙니다(5시부터 방송 예정)"
    },
    {
      "start": "05:00",
      "end": "06:05",
      "title": "무엇이든 물어보세요 스페셜"
    },
    {
      "start": "06:05",
      "end": "06:35",
      "title": "TV 유치원"
    },
    {
      "start": "06:35",
      "end": "07:30",
      "title": "걸어서 세계속으로 트래블홀릭"
    },
    {
      "start": "07:30",
      "end": "08:50",
      "title": "굿모닝 대한민국"
    },
    {
      "start": "08:50",
      "end": "09:30",
      "title": "생생정보 스페셜"
    },
    {
      "start": "09:30",
      "end": "10:10",
      "title": "일일드라마 붉은 진주(89회)"
    },
    {
      "start": "10:10",
      "end": "10:30",
      "title": "KBS 아침 뉴스타임"
    },
    {
      "start": "10:30",
      "end": "11:10",
      "title": "인간극장 스페셜"
    },
    {
      "start": "11:10",
      "end": "12:30",
      "title": "슈퍼맨이 돌아왔다"
    },
    {
      "start": "12:30",
      "end": "13:50",
      "title": "옥탑방의 문제아들"
    },
    {
      "start": "13:50",
      "end": "15:00",
      "title": "무엇이든 물어보세요 스페셜"
    },
    {
      "start": "15:00",
      "end": "15:15",
      "title": "KBS 뉴스타임"
    },
    {
      "start": "15:15",
      "end": "15:45",
      "title": "월드 24"
    },
    {
      "start": "15:45",
      "end": "16:00",
      "title": "마카앤로니 3"
    },
    {
      "start": "16:00",
      "end": "16:30",
      "title": "TV 유치원"
    },
    {
      "start": "16:30",
      "end": "17:00",
      "title": "영상앨범 산"
    },
    {
      "start": "17:00",
      "end": "17:15",
      "title": "강치 아일랜드 2"
    },
    {
      "start": "17:15",
      "end": "17:30",
      "title": "청춘블라썸"
    },
    {
      "start": "17:30",
      "end": "18:00",
      "title": "꿀잼 영화가 좋다"
    },
    {
      "start": "18:00",
      "end": "18:35",
      "title": "경제콘서트"
    },
    {
      "start": "18:35",
      "end": "19:50",
      "title": "2TV 생생정보"
    },
    {
      "start": "19:50",
      "end": "20:30",
      "title": "일일드라마 붉은 진주(90회)"
    },
    {
      "start": "20:30",
      "end": "21:50",
      "title": "슈퍼맨이 돌아왔다"
    },
    {
      "start": "21:50",
      "end": "22:00",
      "title": "생활의 발견 스페셜"
    },
    {
      "start": "22:00",
      "end": "23:30",
      "title": "누난 내게 여자야 2(9회)"
    },
    {
      "start": "23:30",
      "end": "24:00",
      "title": "토일 미니시리즈 결혼의 완성(5회)"
    }
  ],
  "MBC": [
    {
      "start": "00:45",
      "end": "01:05",
      "title": "MBC 뉴스 25"
    },
    {
      "start": "01:05",
      "end": "02:05",
      "title": "MBC 네트워크특선"
    },
    {
      "start": "02:05",
      "end": "05:00",
      "title": "방송 시간이 아닙니다(5시부터 방송 예정)"
    },
    {
      "start": "05:00",
      "end": "06:00",
      "title": "오늘N"
    },
    {
      "start": "06:00",
      "end": "06:25",
      "title": "MBC 뉴스투데이 1부"
    },
    {
      "start": "06:25",
      "end": "07:50",
      "title": "MBC 뉴스투데이 2부"
    },
    {
      "start": "07:50",
      "end": "08:50",
      "title": "생방송 오늘 아침"
    },
    {
      "start": "08:50",
      "end": "09:30",
      "title": "가족관계증명서(12회)"
    },
    {
      "start": "09:30",
      "end": "09:45",
      "title": "930 MBC 뉴스"
    },
    {
      "start": "09:45",
      "end": "10:45",
      "title": "오늘N"
    },
    {
      "start": "10:45",
      "end": "11:15",
      "title": "뽀뽀뽀 좋아좋아 스페셜"
    },
    {
      "start": "11:15",
      "end": "11:45",
      "title": "찾아가는 꾸러기교실"
    },
    {
      "start": "11:45",
      "end": "12:00",
      "title": "베베핀"
    },
    {
      "start": "12:00",
      "end": "12:25",
      "title": "12 MBC 뉴스"
    },
    {
      "start": "12:25",
      "end": "13:25",
      "title": "엄마를 부탁해"
    },
    {
      "start": "13:25",
      "end": "13:55",
      "title": "최고다! 호기심 딱지"
    },
    {
      "start": "13:55",
      "end": "15:55",
      "title": "2시 뉴스 외전"
    },
    {
      "start": "15:55",
      "end": "16:55",
      "title": "기분 좋은 날"
    },
    {
      "start": "16:55",
      "end": "17:10",
      "title": "5시 뉴스와 경제"
    },
    {
      "start": "17:10",
      "end": "18:05",
      "title": "PD수첩"
    },
    {
      "start": "18:05",
      "end": "19:05",
      "title": "오늘N"
    },
    {
      "start": "19:05",
      "end": "19:40",
      "title": "가족관계증명서(13회)"
    },
    {
      "start": "19:40",
      "end": "21:00",
      "title": "MBC 뉴스데스크"
    },
    {
      "start": "21:00",
      "end": "22:30",
      "title": "나 혼자 산다 스페셜"
    },
    {
      "start": "22:30",
      "end": "24:00",
      "title": "라디오스타"
    }
  ],
  "SBS": [
    {
      "start": "00:20",
      "end": "00:50",
      "title": "나이트라인"
    },
    {
      "start": "00:50",
      "end": "01:50",
      "title": "궁금한 이야기 Y"
    },
    {
      "start": "01:50",
      "end": "02:20",
      "title": "꾸러기 탐구생활"
    },
    {
      "start": "02:20",
      "end": "05:00",
      "title": "방송 시간이 아닙니다(5시부터 방송 예정)"
    },
    {
      "start": "05:00",
      "end": "06:00",
      "title": "투데이"
    },
    {
      "start": "06:00",
      "end": "06:25",
      "title": "모닝와이드 (1부)"
    },
    {
      "start": "06:25",
      "end": "07:40",
      "title": "모닝와이드 (2부)"
    },
    {
      "start": "07:40",
      "end": "08:40",
      "title": "모닝와이드 (3부)"
    },
    {
      "start": "08:40",
      "end": "08:50",
      "title": "맨 인 블랙박스 스페셜"
    },
    {
      "start": "08:50",
      "end": "09:55",
      "title": "좋은아침"
    },
    {
      "start": "09:55",
      "end": "10:30",
      "title": "SBS 10 뉴스"
    },
    {
      "start": "10:30",
      "end": "11:00",
      "title": "요리조리 맛있는 수업"
    },
    {
      "start": "11:00",
      "end": "12:00",
      "title": "열린TV 시청자 세상"
    },
    {
      "start": "12:00",
      "end": "12:45",
      "title": "SBS 12 뉴스"
    },
    {
      "start": "12:45",
      "end": "13:00",
      "title": "위시캣 매직카드"
    },
    {
      "start": "13:00",
      "end": "14:00",
      "title": "보석이네 건강 수다"
    },
    {
      "start": "14:00",
      "end": "15:30",
      "title": "뉴스브리핑"
    },
    {
      "start": "15:30",
      "end": "16:00",
      "title": "애니갤러리"
    },
    {
      "start": "16:00",
      "end": "17:00",
      "title": "좋은아침 스페셜"
    },
    {
      "start": "17:00",
      "end": "17:10",
      "title": "SBS 오뉴스"
    },
    {
      "start": "17:10",
      "end": "18:10",
      "title": "TV 동물농장"
    },
    {
      "start": "18:10",
      "end": "19:00",
      "title": "생방송 투데이"
    },
    {
      "start": "19:00",
      "end": "19:50",
      "title": "뉴스헌터스"
    },
    {
      "start": "19:50",
      "end": "21:00",
      "title": "SBS 8 뉴스"
    },
    {
      "start": "21:00",
      "end": "22:50",
      "title": "골 때리는 그녀들"
    },
    {
      "start": "22:50",
      "end": "24:00",
      "title": "김부장(8회)"
    }
  ],
  "JTBC": [
    {
      "start": "00:40",
      "end": "01:30",
      "title": "지킬박사와 가이드 특별판(50회)"
    },
    {
      "start": "01:30",
      "end": "03:10",
      "title": "톡파원 25시(218회)"
    },
    {
      "start": "03:10",
      "end": "05:00",
      "title": "연애전쟁(5회)"
    },
    {
      "start": "05:00",
      "end": "06:00",
      "title": "입만 살았네 스페셜(3회)"
    },
    {
      "start": "06:00",
      "end": "07:00",
      "title": "입만 살았네(7회)"
    },
    {
      "start": "07:00",
      "end": "07:30",
      "title": "슈퍼트론 2(7회)"
    },
    {
      "start": "07:30",
      "end": "08:00",
      "title": "아침&"
    },
    {
      "start": "08:00",
      "end": "09:00",
      "title": "입만 살았네(34회)"
    },
    {
      "start": "09:00",
      "end": "10:00",
      "title": "인생의 갈림길 위대한 선택(33회)"
    },
    {
      "start": "10:00",
      "end": "11:30",
      "title": "냉장고를 부탁해 since 2014(80회)"
    },
    {
      "start": "11:30",
      "end": "13:00",
      "title": "톡파원 25시(218회)"
    },
    {
      "start": "13:00",
      "end": "14:20",
      "title": "아파트(3회)"
    },
    {
      "start": "14:20",
      "end": "15:40",
      "title": "아파트(4회)"
    },
    {
      "start": "15:40",
      "end": "17:00",
      "title": "연애전쟁(5회)"
    },
    {
      "start": "17:00",
      "end": "18:30",
      "title": "이가혁 라이브"
    },
    {
      "start": "18:30",
      "end": "19:50",
      "title": "JTBC 뉴스룸"
    },
    {
      "start": "19:50",
      "end": "20:50",
      "title": "사건반장"
    },
    {
      "start": "20:50",
      "end": "23:10",
      "title": "한문철의 블랙박스 리뷰(179회)"
    },
    {
      "start": "23:10",
      "end": "24:00",
      "title": "연애전쟁(5회)"
    }
  ],
  "MBN": [
    {
      "start": "00:40",
      "end": "01:40",
      "title": "건강히어로(26회)"
    },
    {
      "start": "01:40",
      "end": "02:40",
      "title": "[MBN 스페셜 다큐]리얼도전스토리 하이킥(13회)"
    },
    {
      "start": "02:40",
      "end": "03:40",
      "title": "[MBN 스페셜 다큐]리얼도전스토리 하이킥(14회)"
    },
    {
      "start": "03:40",
      "end": "04:40",
      "title": "[MBN 스페셜 다큐]리얼도전스토리 하이킥(15회)"
    },
    {
      "start": "04:40",
      "end": "05:40",
      "title": "천기누설 스페셜(2407회)"
    },
    {
      "start": "05:40",
      "end": "06:00",
      "title": "재난 대비 이렇게!(87회)"
    },
    {
      "start": "06:00",
      "end": "07:00",
      "title": "당신이 아픈 사이(11회)"
    },
    {
      "start": "07:00",
      "end": "08:00",
      "title": "굿모닝 MBN"
    },
    {
      "start": "08:00",
      "end": "09:20",
      "title": "아침 & 매일경제"
    },
    {
      "start": "09:20",
      "end": "09:30",
      "title": "전국네트워크뉴스"
    },
    {
      "start": "09:30",
      "end": "10:30",
      "title": "매일아침(250회)"
    },
    {
      "start": "10:30",
      "end": "11:40",
      "title": "프레스룸 LIVE"
    },
    {
      "start": "11:40",
      "end": "12:10",
      "title": "오늘도 튼튼 - 우리 가족 건강센터(3회)"
    },
    {
      "start": "12:10",
      "end": "12:40",
      "title": "오늘도 튼튼 - 우리 가족 건강센터(4회)"
    },
    {
      "start": "12:40",
      "end": "13:10",
      "title": "내가 만난 사이코패스(2회)"
    },
    {
      "start": "13:10",
      "end": "14:30",
      "title": "남의 집 귀한 가족(8회)"
    },
    {
      "start": "14:30",
      "end": "16:00",
      "title": "알토란 스페셜(359회)"
    },
    {
      "start": "16:00",
      "end": "17:50",
      "title": "MBN 뉴스와이드"
    },
    {
      "start": "17:50",
      "end": "19:00",
      "title": "더 펀치(3회)"
    },
    {
      "start": "19:00",
      "end": "20:10",
      "title": "MBN 뉴스 7"
    },
    {
      "start": "20:10",
      "end": "21:10",
      "title": "나의 해방일지(40회)"
    },
    {
      "start": "21:10",
      "end": "21:40",
      "title": "무명에서 전설까지(17회)"
    },
    {
      "start": "21:40",
      "end": "22:25",
      "title": "전설의 사내 1부(2회)"
    },
    {
      "start": "22:25",
      "end": "23:20",
      "title": "전설의 사내 2부(2회)"
    },
    {
      "start": "23:20",
      "end": "24:00",
      "title": "전설의 사내 3부(2회)"
    }
  ],
  "TV조선": [
    {
      "start": "00:45",
      "end": "01:15",
      "title": "건강한 아침 해뜰날(53회)"
    },
    {
      "start": "01:15",
      "end": "01:40",
      "title": "장수상회(173회)"
    },
    {
      "start": "01:40",
      "end": "02:40",
      "title": "로드다큐 그리우니 섬이다(8회)"
    },
    {
      "start": "02:40",
      "end": "03:40",
      "title": "로망다큐 가족 플러스(7회)"
    },
    {
      "start": "03:40",
      "end": "04:40",
      "title": "맛있으니 섬이다(4회)"
    },
    {
      "start": "04:40",
      "end": "05:00",
      "title": "TV CHOSUN 재난특집"
    },
    {
      "start": "05:00",
      "end": "06:00",
      "title": "방방곡곡 낭만로드 유랑닥터(68회)"
    },
    {
      "start": "06:00",
      "end": "07:00",
      "title": "인생의 연장전 특별판(68회)"
    },
    {
      "start": "07:00",
      "end": "07:40",
      "title": "건강한 아침 해뜰날(64회)"
    },
    {
      "start": "07:40",
      "end": "08:40",
      "title": "뉴스 퍼레이드"
    },
    {
      "start": "08:40",
      "end": "10:10",
      "title": "신통방통"
    },
    {
      "start": "10:10",
      "end": "11:00",
      "title": "장수상회 특별판(11회)"
    },
    {
      "start": "11:00",
      "end": "11:30",
      "title": "ABC 니니키즈(21회)"
    },
    {
      "start": "11:30",
      "end": "13:00",
      "title": "왕은 무얼 자셨는가(2회)"
    },
    {
      "start": "13:00",
      "end": "14:30",
      "title": "보도본부 핫라인"
    },
    {
      "start": "14:30",
      "end": "16:00",
      "title": "미스트롯 포유(6회)"
    },
    {
      "start": "16:00",
      "end": "17:20",
      "title": "조선의 사랑꾼 베스트(131회)"
    },
    {
      "start": "17:20",
      "end": "19:00",
      "title": "시사팩트 오늘"
    },
    {
      "start": "19:00",
      "end": "20:00",
      "title": "인생의 연장전(200회)"
    },
    {
      "start": "20:00",
      "end": "21:00",
      "title": "퍼펙트 라이프(294회)"
    },
    {
      "start": "21:00",
      "end": "22:00",
      "title": "TV CHOSUN 뉴스9"
    },
    {
      "start": "22:00",
      "end": "22:40",
      "title": "왕은 무얼 자셨는가 1부(3회)"
    },
    {
      "start": "22:40",
      "end": "23:20",
      "title": "왕은 무얼 자셨는가 2부(3회)"
    },
    {
      "start": "23:20",
      "end": "23:40",
      "title": "왕은 무얼 자셨는가 3부(3회)"
    },
    {
      "start": "23:40",
      "end": "24:00",
      "title": "금타는 금요일 특별판(3회)"
    }
  ],
  "채널A": [
    {
      "start": "00:10",
      "end": "01:40",
      "title": "신랑수업 2(18회)"
    },
    {
      "start": "01:40",
      "end": "02:40",
      "title": "채널A 스페셜 도그하우스 영국 시즌4(1회)"
    },
    {
      "start": "02:40",
      "end": "03:40",
      "title": "채널A 스페셜 진품명품을 찾아서 시즌4(1회)"
    },
    {
      "start": "03:40",
      "end": "03:50",
      "title": "채널A 지진 대응 방송"
    },
    {
      "start": "03:50",
      "end": "04:00",
      "title": "채널A 화재 대응 방송"
    },
    {
      "start": "04:00",
      "end": "05:00",
      "title": "채널A 스페셜 구해줘 전원주택 시즌33(3회)"
    },
    {
      "start": "05:00",
      "end": "06:00",
      "title": "몸신의 탄생(80회)"
    },
    {
      "start": "06:00",
      "end": "06:50",
      "title": "건강한 식당(20회)"
    },
    {
      "start": "06:50",
      "end": "07:30",
      "title": "알아야산다(44회)"
    },
    {
      "start": "07:30",
      "end": "08:00",
      "title": "야카 디(22회)"
    },
    {
      "start": "08:00",
      "end": "08:50",
      "title": "행복한 아침"
    },
    {
      "start": "08:50",
      "end": "10:30",
      "title": "김진의 돌직구 쇼"
    },
    {
      "start": "10:30",
      "end": "12:00",
      "title": "하트시그널 5(15회)"
    },
    {
      "start": "12:00",
      "end": "13:20",
      "title": "뉴스A LIVE"
    },
    {
      "start": "13:20",
      "end": "14:20",
      "title": "잘 살면 좋잖아(33회)"
    },
    {
      "start": "14:20",
      "end": "14:50",
      "title": "온고지신 시즌3(5회)"
    },
    {
      "start": "14:50",
      "end": "15:50",
      "title": "오늘은 아빠랑(3회)"
    },
    {
      "start": "15:50",
      "end": "17:10",
      "title": "야구여왕 2 스페셜(2회)"
    },
    {
      "start": "17:10",
      "end": "19:00",
      "title": "뉴스 TOP10"
    },
    {
      "start": "19:00",
      "end": "20:00",
      "title": "뉴스A"
    },
    {
      "start": "20:00",
      "end": "21:00",
      "title": "스타건강랭킹 넘버원(54회)"
    },
    {
      "start": "21:00",
      "end": "22:00",
      "title": "뉴스A CITY LIVE"
    },
    {
      "start": "22:00",
      "end": "24:00",
      "title": "개와 늑대의 시간 2(27회)"
    }
  ]
}